errortrace_pro/__init__.py
errortrace_pro/cli.py
errortrace_pro/cloud_logger.py
errortrace_pro/handler.py
errortrace_pro/solutions.py
errortrace_pro/visualizer.py
errortrace_pro/data/solutions.json
errortrace_pro-0.3.0.dist-info/LICENSE
errortrace_pro-0.3.0.dist-info/METADATA
errortrace_pro-0.3.0.dist-info/WHEEL
errortrace_pro-0.3.0.dist-info/entry_points.txt
errortrace_pro-0.3.0.dist-info/top_level.txt
errortrace_pro-0.3.0.dist-info/RECORD
