Metadata-Version: 2.1
Name: errortrace-pro
Version: 0.3.0
Summary: Enhanced exception handling for Python with visual tracebacks, solution suggestions, and cloud logging
Home-page: https://github.com/Hamed233/ErrorTrace-Pro
Author: Hamed Esam
Author-email: Hamed Esam <info@hamedesam.info>
License: MIT
Project-URL: Homepage, https://github.com/Hamed233/ErrorTrace-Pro
Project-URL: Issues, https://github.com/Hamed233/ErrorTrace-Pro/issues
Keywords: exception,traceback,debugging,error handling,cloud logging
Classifier: Development Status :: 4 - Beta
Classifier: Environment :: Console
Classifier: Intended Audience :: Developers
Classifier: License :: OSI Approved :: MIT License
Classifier: Operating System :: OS Independent
Classifier: Programming Language :: Python
Classifier: Programming Language :: Python :: 3
Classifier: Programming Language :: Python :: 3.7
Classifier: Programming Language :: Python :: 3.8
Classifier: Programming Language :: Python :: 3.9
Classifier: Programming Language :: Python :: 3.10
Classifier: Programming Language :: Python :: 3.11
Classifier: Topic :: Software Development :: Debuggers
Classifier: Topic :: Software Development :: Libraries :: Python Modules
Requires-Python: >=3.7
License-File: LICENSE
Requires-Dist: colorama >=0.4.4
Requires-Dist: rich >=13.8.1
Provides-Extra: all
Requires-Dist: rich >=10.0.0 ; extra == 'all'
Requires-Dist: click >=7.0.0 ; extra == 'all'
Requires-Dist: flask >=2.0.0 ; extra == 'all'
Provides-Extra: cli
Requires-Dist: click >=7.0.0 ; extra == 'cli'
Provides-Extra: dev
Requires-Dist: pytest >=7.0.0 ; extra == 'dev'
Requires-Dist: black >=23.0.0 ; extra == 'dev'
Requires-Dist: flake8 >=6.0.0 ; extra == 'dev'
Requires-Dist: isort >=5.0.0 ; extra == 'dev'
Requires-Dist: build >=0.10.0 ; extra == 'dev'
Requires-Dist: twine >=4.0.0 ; extra == 'dev'
Provides-Extra: rich
Requires-Dist: rich >=10.0.0 ; extra == 'rich'
